yahdlc.cpython-310-x86_64-linux-gnu.so
python4yahdlc-1.3.5.dist-info/METADATA
python4yahdlc-1.3.5.dist-info/LICENSE.txt
python4yahdlc-1.3.5.dist-info/top_level.txt
python4yahdlc-1.3.5.dist-info/RECORD
python4yahdlc-1.3.5.dist-info/WHEEL
