Metadata-Version: 2.1
Name: python4yahdlc
Version: 1.3.5
Summary: Python binding of the yahdlc library allowing to encode and decode HDLC frames.
Home-page: https://github.com/SkypLabs/python4yahdlc
Author: Paul-Emmanuel Raoul
Author-email: skyper@skyplabs.net
License: GPLv3
Project-URL: Bug Tracker, https://github.com/SkypLabs/python4yahdlc/issues
Project-URL: Source Code, https://github.com/SkypLabs/python4yahdlc
Keywords: hdlc,yahdlc,binding,network
Classifier: Development Status :: 5 - Production/Stable
Classifier: Intended Audience :: Developers
Classifier: Topic :: Software Development :: Libraries :: Python Modules
Classifier: Natural Language :: English
Classifier: Programming Language :: C
Classifier: Programming Language :: Python :: 3 :: Only
Classifier: Programming Language :: Python :: 3.7
Classifier: Programming Language :: Python :: 3.8
Classifier: Programming Language :: Python :: 3.9
Classifier: Programming Language :: Python :: 3.10
Classifier: Programming Language :: Python :: 3.11
Classifier: License :: OSI Approved :: GNU General Public License v3 (GPLv3)
Requires-Python: <4,>=3.7
License-File: LICENSE.txt
Provides-Extra: examples
Requires-Dist: fysom ; extra == 'examples'
Requires-Dist: pyserial ; extra == 'examples'
Provides-Extra: tests
Requires-Dist: black ; extra == 'tests'
Requires-Dist: ruff ; extra == 'tests'
Requires-Dist: tox ; extra == 'tests'
